lighttuner/__init__.py
lighttuner/config/__init__.py
lighttuner/config/meta.py
lighttuner/hpo/__init__.py
lighttuner/hpo/algorithm/__init__.py
lighttuner/hpo/algorithm/base/__init__.py
lighttuner/hpo/algorithm/base/algorithm.py
lighttuner/hpo/algorithm/base/model.py
lighttuner/hpo/algorithm/bayes/__init__.py
lighttuner/hpo/algorithm/bayes/algorithm.py
lighttuner/hpo/algorithm/bayes/allocation.py
lighttuner/hpo/algorithm/bayes/utils.py
lighttuner/hpo/algorithm/grid/__init__.py
lighttuner/hpo/algorithm/grid/algorithm.py
lighttuner/hpo/algorithm/grid/allocation.py
lighttuner/hpo/algorithm/random/__init__.py
lighttuner/hpo/algorithm/random/algorithm.py
lighttuner/hpo/algorithm/random/allocation.py
lighttuner/hpo/runner/__init__.py
lighttuner/hpo/runner/event.py
lighttuner/hpo/runner/hpo.py
lighttuner/hpo/runner/log.py
lighttuner/hpo/runner/model.py
lighttuner/hpo/runner/result.py
lighttuner/hpo/runner/runner.py
lighttuner/hpo/runner/signal.py
lighttuner/hpo/space/__init__.py
lighttuner/hpo/space/base.py
lighttuner/hpo/space/continuous.py
lighttuner/hpo/space/fixed.py
lighttuner/hpo/space/separate.py
lighttuner/hpo/utils/__init__.py
lighttuner/hpo/utils/event.py
lighttuner/hpo/utils/lock.py
lighttuner/hpo/utils/ranking.py
lighttuner/hpo/utils/service.py
lighttuner/hpo/utils/string.py
lighttuner/hpo/utils/type.py
lighttuner/hpo/utils/math/__init__.py
lighttuner/hpo/utils/math/normal.py
lighttuner/hpo/value/__init__.py
lighttuner/hpo/value/funcs.py
lighttuner/hpo/value/struct.py
lighttuner/hpo/value/value.py
lighttuner/scheduler/__init__.py
lighttuner/scheduler/cross_platform_mp_queue.py
lighttuner/scheduler/task_scheduler.py
lighttuner-0.0.1.dist-info/LICENSE
lighttuner-0.0.1.dist-info/METADATA
lighttuner-0.0.1.dist-info/WHEEL
lighttuner-0.0.1.dist-info/top_level.txt
lighttuner-0.0.1.dist-info/RECORD
