Metadata-Version: 2.1
Name: lighttuner
Version: 0.0.1
Summary: A simple tool for automatic parameter tuning.
Home-page: https://gitlab.bj.sensetime.com/open-XLab/cell/di-toolkit
Author: HansBug
Author-email: hansbug@buaa.edu.cn
License: Apache License, Version 2.0
Keywords: A simple tool for automatic parameter tuning.
Classifier: Development Status :: 5 - Production/Stable
Classifier: Intended Audience :: Developers
Classifier: License :: OSI Approved :: Apache Software License
Classifier: Programming Language :: Python
Classifier: Programming Language :: Python :: 3
Classifier: Programming Language :: Python :: 3.7
Classifier: Programming Language :: Python :: 3.8
Classifier: Programming Language :: Python :: 3.9
Classifier: Programming Language :: Python :: 3.10
Requires-Python: >=3.7
License-File: LICENSE
Requires-Dist: hbutils (<1,>=0.6.11)
Requires-Dist: rich (>=12.2.0)
Requires-Dist: tabulate (>=0.8.9)
Requires-Dist: inflection (>=0.5.1)
Requires-Dist: numpy (>=1.18.0)
Requires-Dist: scipy (>=0.14.0)
Requires-Dist: scikit-learn (>=0.18.0)
Requires-Dist: ruamel.yaml (>=0.17.2)
Requires-Dist: psutil (>=5.7.0)
Requires-Dist: DI-toolkit (>=0.0.2)
Provides-Extra: doc
Requires-Dist: Jinja2 (~=3.0.0) ; extra == 'doc'
Requires-Dist: sphinx (~=3.2.0) ; extra == 'doc'
Requires-Dist: sphinx-rtd-theme (~=0.4.3) ; extra == 'doc'
Requires-Dist: enum-tools ; extra == 'doc'
Requires-Dist: sphinx-toolbox ; extra == 'doc'
Requires-Dist: plantumlcli (>=0.0.2) ; extra == 'doc'
Requires-Dist: packaging ; extra == 'doc'
Requires-Dist: sphinx-multiversion (~=0.2.4) ; extra == 'doc'
Requires-Dist: where (~=1.0.2) ; extra == 'doc'
Requires-Dist: easydict (<2,>=1.7) ; extra == 'doc'
Requires-Dist: numpy (<2,>=1.19) ; extra == 'doc'
Provides-Extra: style
Requires-Dist: yapf (==0.29.0) ; extra == 'style'
Requires-Dist: flake8 (<5,>=3) ; extra == 'style'
Provides-Extra: test
Requires-Dist: coverage (>=5) ; extra == 'test'
Requires-Dist: mock (>=4.0.3) ; extra == 'test'
Requires-Dist: flake8 (~=3.5) ; extra == 'test'
Requires-Dist: testfixtures (>=6.18.5) ; extra == 'test'
Requires-Dist: pytest (~=6.2.5) ; extra == 'test'
Requires-Dist: pytest-cov (~=3.0.0) ; extra == 'test'
Requires-Dist: pytest-mock (~=3.6.1) ; extra == 'test'
Requires-Dist: pytest-xdist (>=1.34.0) ; extra == 'test'
Requires-Dist: pytest-rerunfailures (~=10.2) ; extra == 'test'
Requires-Dist: pytest-timeout (~=2.0.2) ; extra == 'test'
Requires-Dist: pytest-benchmark (~=3.4.0) ; extra == 'test'
Requires-Dist: easydict (<2,>=1.7) ; extra == 'test'
Requires-Dist: testtools (>=2) ; extra == 'test'
Requires-Dist: numpy (<2,>=1.19) ; extra == 'test'
Requires-Dist: where (>=1.0.2) ; extra == 'test'
